aeiva/README.md
aeiva/__init__.py
aeiva/action/README.md
aeiva/action/__init__.py
aeiva/action/action.py
aeiva/action/action_system.py
aeiva/action/experience.py
aeiva/action/plan.py
aeiva/action/procedure.py
aeiva/action/skill.py
aeiva/action/status.py
aeiva/action/step.py
aeiva/action/task.py
aeiva/action/test.py
aeiva/admin/README.md
aeiva/admin/__init__.py
aeiva/agent/__init__.py
aeiva/agent/agent.py
aeiva/agent/base_agent.py
aeiva/cognition/README.md
aeiva/cognition/__init__.py
aeiva/cognition/brain/__init__.py
aeiva/cognition/brain/brain.py
aeiva/cognition/brain/llm_brain.py
aeiva/cognition/brain/test.py
aeiva/cognition/cognition_system.py
aeiva/cognition/emotion/__init__.py
aeiva/cognition/emotion/emotion.py
aeiva/cognition/emotion/emotion_categorical.py
aeiva/cognition/emotion/emotion_category.py
aeiva/cognition/emotion/emotion_circumplex.py
aeiva/cognition/emotion/emotion_componential.py
aeiva/cognition/emotion/emotion_hybrid.py
aeiva/cognition/emotion/emotion_occ.py
aeiva/cognition/emotion/emotion_pad.py
aeiva/cognition/emotion/emotion_plutchik.py
aeiva/cognition/emotion/exceptions.py
aeiva/cognition/emotion/simple_emotion.py
aeiva/cognition/input_interpreter/input_interpreter.py
aeiva/cognition/input_interpreter/llm_input_interpreter.py
aeiva/cognition/input_interpreter/simple_input_interpreter.py
aeiva/cognition/memory/__init__.py
aeiva/cognition/memory/memory.py
aeiva/cognition/memory/memory_cleaner.py
aeiva/cognition/memory/memory_config.py
aeiva/cognition/memory/memory_link.py
aeiva/cognition/memory/memory_organizer.py
aeiva/cognition/memory/memory_palace.py
aeiva/cognition/memory/memory_parameterizer.py
aeiva/cognition/memory/memory_retriever.py
aeiva/cognition/memory/memory_skillizer.py
aeiva/cognition/memory/memory_storage.py
aeiva/cognition/memory/memory_structurer.py
aeiva/cognition/memory/memory_unit.py
aeiva/cognition/memory/memory_utils.py
aeiva/cognition/memory/simple_memory.py
aeiva/cognition/memory/storage_config.py
aeiva-0.8.2.6.dist-info/LICENSE
aeiva-0.8.2.6.dist-info/METADATA
aeiva-0.8.2.6.dist-info/WHEEL
aeiva-0.8.2.6.dist-info/entry_points.txt
aeiva-0.8.2.6.dist-info/RECORD
