Metadata-Version: 2.1
Name: aeiva
Version: 0.8.2.6
Summary: aeiva is a general AI agent framework
License: Apache License Version 2.0
Author: Bang Liu
Author-email: chatsci.ai@gmail.com
Requires-Python: >=3.10,<3.14
Classifier: License :: Other/Proprietary License
Classifier: Programming Language :: Python :: 3
Classifier: Programming Language :: Python :: 3.10
Classifier: Programming Language :: Python :: 3.11
Classifier: Programming Language :: Python :: 3.12
Classifier: Programming Language :: Python :: 3.13
Requires-Dist: appium-python-client (==4.3.0)
Requires-Dist: arxiv (==2.1.3)
Requires-Dist: chromadb (==0.5.20)
Requires-Dist: click (==8.1.7)
Requires-Dist: deepspeed (==0.15.4)
Requires-Dist: docker (==6.1.3)
Requires-Dist: fastapi (==0.115.5)
Requires-Dist: gradio (==5.6.0)
Requires-Dist: importlib-metadata (==8.5.0)
Requires-Dist: litellm (==1.52.15)
Requires-Dist: mammoth (==1.8.0)
Requires-Dist: markdownify (==0.13.1)
Requires-Dist: matplotlib (==3.9.3)
Requires-Dist: mkdocs (==1.6.1)
Requires-Dist: moviepy (==2.1.1)
Requires-Dist: neo4j (==5.26.0)
Requires-Dist: networkx (==3.4.1)
Requires-Dist: numpy (==2.1.3)
Requires-Dist: ocrmypdf (==16.6.2)
Requires-Dist: opencv-python (==4.10.0.84)
Requires-Dist: pandas (==2.2.3)
Requires-Dist: pathspec (==0.12.1)
Requires-Dist: pdfplumber (==0.11.4)
Requires-Dist: psutil (==5.9.8)
Requires-Dist: psycopg2 (==2.9.10)
Requires-Dist: pyautogui (==0.9.41)
Requires-Dist: pydantic (==2.10.1)
Requires-Dist: pygame (==2.6.1)
Requires-Dist: pymilvus (==2.4.9)
Requires-Dist: pymupdf4llm (==0.0.17)
Requires-Dist: pypdf (==5.1.0)
Requires-Dist: pytesseract (==0.3.13)
Requires-Dist: pytest (==8.3.3)
Requires-Dist: python-docx (==1.1.2)
Requires-Dist: pytorch-lightning (==2.4.0)
Requires-Dist: pywinauto (==0.6.6)
Requires-Dist: qdrant-client (==1.12.1)
Requires-Dist: requests (==2.32.3)
Requires-Dist: scipy (==1.14.1)
Requires-Dist: selenium (==4.26.1)
Requires-Dist: setuptools (==75.1.0)
Requires-Dist: soundfile (==0.12.1)
Requires-Dist: torch (==2.4.1)
Requires-Dist: torchvision (==0.19.1)
Requires-Dist: tqdm (==4.66.5)
Requires-Dist: transformers (==4.45.2)
Requires-Dist: uvicorn (==0.32.1)
